infomark_cli/__init__.py
infomark_cli/argparse_translator/__init__.py
infomark_cli/argparse_translator/argparse_argument.py
infomark_cli/argparse_translator/argparse_class_processor.py
infomark_cli/argparse_translator/argparse_translator.py
infomark_cli/argparse_translator/obbject_registry.py
infomark_cli/argparse_translator/reference_processor.py
infomark_cli/argparse_translator/utils.py
infomark_cli/assets/routines/routine_example.infomark
infomark_cli/assets/styles/default/Consolas.ttf
infomark_cli/assets/styles/default/dark.mpfstyle.json
infomark_cli/assets/styles/default/dark.mplrc.json
infomark_cli/assets/styles/default/dark.mplstyle
infomark_cli/assets/styles/default/dark.pltstyle.json
infomark_cli/assets/styles/default/dark.richstyle.json
infomark_cli/assets/styles/default/light.mpfstyle.json
infomark_cli/assets/styles/default/light.mplrc.json
infomark_cli/assets/styles/default/light.mplstyle
infomark_cli/assets/styles/default/light.pltstyle.json
infomark_cli/assets/styles/default/light.richstyle.json
infomark_cli/assets/styles/default/tables.pltstyle.json
infomark_cli/cli.py
infomark_cli/config/__init__.py
infomark_cli/config/completer.py
infomark_cli/config/infomark_console.py
infomark_cli/config/infomark_constants.py
infomark_cli/config/infomark_menu_text.py
infomark_cli/config/setup.py
infomark_cli/config/style.py
infomark_cli/controllers/choices.py
infomark_cli/controllers/infomark_controller_base.py
infomark_cli/controllers/infomark_controller_cli.py
infomark_cli/controllers/infomark_platform_controller_base.py
infomark_cli/controllers/infomark_script_parser.py
infomark_cli/controllers/platform_controller_factory.py
infomark_cli/controllers/settings_controller.py
infomark_cli/controllers/utils.py
infomark_cli/models/settings.py
infomark_cli/session.py
infomark_cli/utils/utils.py
infomark_cli-1.1.1.dist-info/METADATA
infomark_cli-1.1.1.dist-info/WHEEL
infomark_cli-1.1.1.dist-info/entry_points.txt
infomark_cli-1.1.1.dist-info/RECORD
